{
	"textures": [
		{
			"image": "ui.png",
			"format": "RGBA8888",
			"size": {
				"w": 480,
				"h": 528
			},
			"scale": 1,
			"frames": [
                {
					"filename": "button-white",
					"rotated": false,
					"trimmed": false,
					"sourceSize": {
						"w": 48,
						"h": 48
					},
					"spriteSourceSize": {
						"x": 0,
						"y": 0,
						"w": 48,
						"h": 48
					},
					"frame": {
						"x": 0,
						"y": 32,
						"w": 48,
						"h": 48
					}
				},
                {
					"filename": "button-yellow",
					"rotated": false,
					"trimmed": false,
					"sourceSize": {
						"w": 48,
						"h": 48
					},
					"spriteSourceSize": {
						"x": 0,
						"y": 0,
						"w": 48,
						"h": 48
					},
					"frame": {
						"x": 96,
						"y": 32,
						"w": 48,
						"h": 48
					}
				},
                {
					"filename": "button-green",
					"rotated": false,
					"trimmed": false,
					"sourceSize": {
						"w": 48,
						"h": 48
					},
					"spriteSourceSize": {
						"x": 0,
						"y": 0,
						"w": 48,
						"h": 48
					},
					"frame": {
						"x": 192,
						"y": 32,
						"w": 48,
						"h": 48
					}
				},
				{
					"filename": "button-orange",
					"rotated": false,
					"trimmed": false,
					"sourceSize": {
						"w": 48,
						"h": 48
					},
					"spriteSourceSize": {
						"x": 0,
						"y": 0,
						"w": 48,
						"h": 48
					},
					"frame": {
						"x": 288,
						"y": 32,
						"w": 48,
						"h": 48
					}
				},
				{
					"filename": "button-blue",
					"rotated": false,
					"trimmed": false,
					"sourceSize": {
						"w": 48,
						"h": 48
					},
					"spriteSourceSize": {
						"x": 0,
						"y": 0,
						"w": 48,
						"h": 48
					},
					"frame": {
						"x": 384,
						"y": 32,
						"w": 48,
						"h": 48
					}
				},
				{
					"filename": "toggle-off",
					"rotated": false,
					"trimmed": false,
					"sourceSize": {
						"w": 16,
						"h": 16
					},
					"spriteSourceSize": {
						"x": 0,
						"y": 0,
						"w": 16,
						"h": 16
					},
					"frame": {
						"x": 48,
						"y": 80,
						"w": 16,
						"h": 16
					}
				},
				{
					"filename": "toggle-white",
					"rotated": false,
					"trimmed": false,
					"sourceSize": {
						"w": 16,
						"h": 16
					},
					"spriteSourceSize": {
						"x": 0,
						"y": 0,
						"w": 16,
						"h": 16
					},
					"frame": {
						"x": 48,
						"y": 96,
						"w": 16,
						"h": 16
					}
				},
				{
					"filename": "toggle-yellow",
					"rotated": false,
					"trimmed": false,
					"sourceSize": {
						"w": 16,
						"h": 16
					},
					"spriteSourceSize": {
						"x": 0,
						"y": 0,
						"w": 16,
						"h": 16
					},
					"frame": {
						"x": 144,
						"y": 96,
						"w": 16,
						"h": 16
					}
				},
				{
					"filename": "toggle-green",
					"rotated": false,
					"trimmed": false,
					"sourceSize": {
						"w": 16,
						"h": 16
					},
					"spriteSourceSize": {
						"x": 0,
						"y": 0,
						"w": 16,
						"h": 16
					},
					"frame": {
						"x": 240,
						"y": 96,
						"w": 16,
						"h": 16
					}
				},
				{
					"filename": "toggle-orange",
					"rotated": false,
					"trimmed": false,
					"sourceSize": {
						"w": 16,
						"h": 16
					},
					"spriteSourceSize": {
						"x": 0,
						"y": 0,
						"w": 16,
						"h": 16
					},
					"frame": {
						"x": 336,
						"y": 96,
						"w": 16,
						"h": 16
					}
				},
				{
					"filename": "toggle-blue",
					"rotated": false,
					"trimmed": false,
					"sourceSize": {
						"w": 16,
						"h": 16
					},
					"spriteSourceSize": {
						"x": 0,
						"y": 0,
						"w": 16,
						"h": 16
					},
					"frame": {
						"x": 432,
						"y": 96,
						"w": 16,
						"h": 16
					}
				},
				{
					"filename": "panel-white",
					"rotated": false,
					"trimmed": false,
					"sourceSize": {
						"w": 48,
						"h": 48
					},
					"spriteSourceSize": {
						"x": 0,
						"y": 0,
						"w": 48,
						"h": 48
					},
					"frame": {
						"x": 0,
						"y": 144,
						"w": 48,
						"h": 48
					}
				},
				{
					"filename": "panel-yellow",
					"rotated": false,
					"trimmed": false,
					"sourceSize": {
						"w": 48,
						"h": 48
					},
					"spriteSourceSize": {
						"x": 0,
						"y": 0,
						"w": 48,
						"h": 48
					},
					"frame": {
						"x": 96,
						"y": 128,
						"w": 48,
						"h": 48
					}
				},
				{
					"filename": "panel-green",
					"rotated": false,
					"trimmed": false,
					"sourceSize": {
						"w": 48,
						"h": 48
					},
					"spriteSourceSize": {
						"x": 0,
						"y": 0,
						"w": 48,
						"h": 48
					},
					"frame": {
						"x": 192,
						"y": 128,
						"w": 48,
						"h": 48
					}
				},
				{
					"filename": "panel-orange",
					"rotated": false,
					"trimmed": false,
					"sourceSize": {
						"w": 48,
						"h": 48
					},
					"spriteSourceSize": {
						"x": 0,
						"y": 0,
						"w": 48,
						"h": 48
					},
					"frame": {
						"x": 288,
						"y": 128,
						"w": 48,
						"h": 48
					}
				},
				{
					"filename": "panel-blue",
					"rotated": false,
					"trimmed": false,
					"sourceSize": {
						"w": 48,
						"h": 48
					},
					"spriteSourceSize": {
						"x": 0,
						"y": 0,
						"w": 48,
						"h": 48
					},
					"frame": {
						"x": 384,
						"y": 128,
						"w": 48,
						"h": 48
					}
				},
				{
					"filename": "divider-horizontal",
					"rotated": false,
					"trimmed": false,
					"sourceSize": {
						"w": 48,
						"h": 16
					},
					"spriteSourceSize": {
						"x": 0,
						"y": 0,
						"w": 48,
						"h": 16
					},
					"frame": {
						"x": 48,
						"y": 128,
						"w": 48,
						"h": 16
					}
				},
				{
					"filename": "divider-vertical",
					"rotated": false,
					"trimmed": false,
					"sourceSize": {
						"w": 16,
						"h": 48
					},
					"spriteSourceSize": {
						"x": 0,
						"y": 0,
						"w": 16,
						"h": 48
					},
					"frame": {
						"x": 16,
						"y": 488,
						"w": 16,
						"h": 48
					}
				}
            ]
		}
	],
	"meta": {
		"app": "Manual",
		"version": "0.0"
	}
}